norconsult/__init__.py
norconsult/all_formulas.py
norconsult/all_simple.py
norconsult/epanet.py
norconsult/other_utilities.py
norconsult/sosi_calc.py
test/__init__.py
test/testcodes.py
norconsult-0.2.0.dist-info/METADATA
norconsult-0.2.0.dist-info/WHEEL
norconsult-0.2.0.dist-info/top_level.txt
norconsult-0.2.0.dist-info/RECORD
